aft_pt/__init__.py
aft_pt/aft_pytorch.py
aft_pt-0.1.0.dist-info/LICENSE
aft_pt-0.1.0.dist-info/METADATA
aft_pt-0.1.0.dist-info/WHEEL
aft_pt-0.1.0.dist-info/top_level.txt
aft_pt-0.1.0.dist-info/RECORD
