Metadata-Version: 2.1
Name: aft-pt
Version: 0.1.0
Summary: Attention Free Transformer - Pytorch
Home-page: https://github.com/shendezhou/aft-pytorch
Author: Shen Dezhou
Author-email: tsinghua9boy@sina.com
License: MIT
Keywords: artificial intelligence,deep learning,attention free transformer,self-attention,transformer,natural language processing
Platform: UNKNOWN
Classifier: Development Status :: 4 - Beta
Classifier: Intended Audience :: Developers
Classifier: Topic :: Scientific/Engineering :: Artificial Intelligence
Classifier: License :: OSI Approved :: MIT License
Classifier: Programming Language :: Python :: 3.6
Classifier: Programming Language :: Python :: 3.7
Classifier: Programming Language :: Python :: 3.8
Classifier: Programming Language :: Python :: 3.9
Classifier: Programming Language :: Python :: 3.10
License-File: LICENSE
Requires-Dist: torch (>=1.6)
